{"v":"5.9.6","fr":30,"ip":0,"op":65,"w":1000,"h":1000,"nm":"3) Writing","ddd":0,"assets":[],"layers":[{"ddd":0,"ind":1,"ty":4,"nm":"L Arm","parent":17,"sr":1,"ks":{"o":{"a":0,"k":100,"ix":11},"r":{"a":1,"k":[{"i":{"x":[0.25],"y":[1]},"o":{"x":[0.333],"y":[0]},"t":0,"s":[0]},{"i":{"x":[0.25],"y":[1]},"o":{"x":[0.333],"y":[0]},"t":10,"s":[5]},{"i":{"x":[0.833],"y":[1]},"o":{"x":[0.333],"y":[0]},"t":25,"s":[-2]},{"i":{"x":[0.25],"y":[1]},"o":{"x":[0.167],"y":[0]},"t":45,"s":[-3.5]},{"t":60,"s":[0]}],"ix":10},"p":{"a":0,"k":[26.31,247.197,0],"ix":2,"l":2},"a":{"a":0,"k":[120.135,8.803,0],"ix":1,"l":2},"s":{"a":0,"k":[100,100,100],"ix":6,"l":2}},"ao":0,"shapes":[{"ty":"gr","it":[{"ind":0,"ty":"sh","ix":1,"ks":{"a":0,"k":{"i":[[0,0],[6.377,-61.381],[-15.259,18.021],[58.685,67.327]],"o":[[0,0],[-16.604,159.835],[29.977,-35.402],[-19.589,-22.474]],"v":[[48.833,-86.009],[-18.102,-0.938],[137.144,158.15],[66.609,28.844]],"c":true},"ix":2},"nm":"Path 1","mn":"ADBE Vector Shape - Group","hd":false},{"ty":"fl","c":{"a":0,"k":[0.098039223166,0.098039223166,0.098039223166,1],"ix":4},"o":{"a":0,"k":100,"ix":5},"r":1,"bm":0,"nm":"Fill 1","mn":"ADBE Vector Graphic - Fill","hd":false},{"ty":"tr","p":{"a":0,"k":[71.215,86.259],"ix":2},"a":{"a":0,"k":[0,0],"ix":1},"s":{"a":0,"k":[100,100],"ix":3},"r":{"a":0,"k":0,"ix":6},"o":{"a":0,"k":100,"ix":7},"sk":{"a":0,"k":0,"ix":4},"sa":{"a":0,"k":0,"ix":5},"nm":"Transform"}],"nm":"Group 1","np":2,"cix":2,"bm":0,"ix":1,"mn":"ADBE Vector Group","hd":false}],"ip":0,"op":65,"st":0,"ct":1,"bm":0},{"ddd":0,"ind":2,"ty":4,"nm":"Board","parent":1,"sr":1,"ks":{"o":{"a":0,"k":100,"ix":11},"r":{"a":0,"k":0,"ix":10},"p":{"a":0,"k":[265.796,209.952,0],"ix":2,"l":2},"a":{"a":0,"k":[133.04,169.234,0],"ix":1,"l":2},"s":{"a":0,"k":[90.909,90.909,100],"ix":6,"l":2}},"ao":0,"shapes":[{"ty":"gr","it":[{"ty":"gr","it":[{"ind":0,"ty":"sh","ix":1,"ks":{"a":0,"k":{"i":[[-8.664,0],[0,0],[-1.312,7.338],[33.868,68.042],[0,0],[0,-8.664],[0,0]],"o":[[0,0],[7.715,0],[-102.599,-76.936],[0,0],[-8.664,0],[0,0],[0,8.664]],"v":[[-101.277,150.813],[101.537,150.813],[116.965,137.901],[-99.215,-150.813],[-101.277,-150.813],[-116.965,-135.126],[-116.965,135.125]],"c":true},"ix":2},"nm":"Path 1","mn":"ADBE Vector Shape - Group","hd":false},{"ty":"fl","c":{"a":0,"k":[0.670588235294,0.219607858097,0.211764720842,1],"ix":4},"o":{"a":0,"k":100,"ix":5},"r":1,"bm":0,"nm":"Fill 1","mn":"ADBE Vector Graphic - Fill","hd":false},{"ty":"tr","p":{"a":0,"k":[117.215,187.404],"ix":2},"a":{"a":0,"k":[0,0],"ix":1},"s":{"a":0,"k":[100,100],"ix":3},"r":{"a":0,"k":0,"ix":6},"o":{"a":0,"k":100,"ix":7},"sk":{"a":0,"k":0,"ix":4},"sa":{"a":0,"k":0,"ix":5},"nm":"Transform"}],"nm":"Group 1","np":2,"cix":2,"bm":0,"ix":1,"mn":"ADBE Vector Group","hd":false},{"ty":"gr","it":[{"ind":0,"ty":"sh","ix":1,"ks":{"a":0,"k":{"i":[[0,0],[2.551,0],[0,0],[0,0],[0.277,-2.536],[0,0],[0,0],[0,0]],"o":[[-0.277,-2.536],[0,0],[0,0],[-2.551,0],[0,0],[0,0],[0,0],[0,0]],"v":[[27.292,-4.315],[22.322,-8.771],[0,-8.771],[-22.321,-8.771],[-27.291,-4.315],[-28.724,8.771],[0,8.771],[28.724,8.771]],"c":true},"ix":2},"nm":"Path 1","mn":"ADBE Vector Shape - Group","hd":false},{"ty":"fl","c":{"a":0,"k":[0.90588241278,0.662745098039,0.219607858097,1],"ix":4},"o":{"a":0,"k":100,"ix":5},"r":1,"bm":0,"nm":"Fill 1","mn":"ADBE Vector Graphic - Fill","hd":false},{"ty":"tr","p":{"a":0,"k":[117.344,9.021],"ix":2},"a":{"a":0,"k":[0,0],"ix":1},"s":{"a":0,"k":[100,100],"ix":3},"r":{"a":0,"k":0,"ix":6},"o":{"a":0,"k":100,"ix":7},"sk":{"a":0,"k":0,"ix":4},"sa":{"a":0,"k":0,"ix":5},"nm":"Transform"}],"nm":"Group 2","np":2,"cix":2,"bm":0,"ix":2,"mn":"ADBE Vector Group","hd":false},{"ty":"gr","it":[{"ind":0,"ty":"sh","ix":1,"ks":{"a":0,"k":{"i":[[2.761,0],[0,0],[0,2.761],[0,0],[0,0],[0,0]],"o":[[0,0],[-2.761,0],[0,0],[0,0],[0,0],[0,2.761]],"v":[[47.943,8.655],[-47.943,8.655],[-52.943,3.655],[-52.943,-8.655],[52.943,-8.655],[52.943,3.655]],"c":true},"ix":2},"nm":"Path 1","mn":"ADBE Vector Shape - Group","hd":false},{"ty":"fl","c":{"a":0,"k":[0.90588241278,0.662745098039,0.219607858097,1],"ix":4},"o":{"a":0,"k":100,"ix":5},"r":1,"bm":0,"nm":"Fill 1","mn":"ADBE Vector Graphic - Fill","hd":false},{"ty":"tr","p":{"a":0,"k":[117.345,43.758],"ix":2},"a":{"a":0,"k":[0,0],"ix":1},"s":{"a":0,"k":[100,100],"ix":3},"r":{"a":0,"k":0,"ix":6},"o":{"a":0,"k":100,"ix":7},"sk":{"a":0,"k":0,"ix":4},"sa":{"a":0,"k":0,"ix":5},"nm":"Transform"}],"nm":"Group 3","np":2,"cix":2,"bm":0,"ix":3,"mn":"ADBE Vector Group","hd":false},{"ty":"gr","it":[{"ind":0,"ty":"sh","ix":1,"ks":{"a":0,"k":{"i":[[0,0],[0,0],[0,0],[-2.761,0],[0,0],[0,-2.761]],"o":[[0,0],[0,0],[0,-2.761],[0,0],[2.761,0],[0,0]],"v":[[52.943,8.655],[-52.943,8.655],[-52.943,-3.655],[-47.943,-8.655],[47.943,-8.655],[52.943,-3.655]],"c":true},"ix":2},"nm":"Path 1","mn":"ADBE Vector Shape - Group","hd":false},{"ty":"fl","c":{"a":0,"k":[0.925490255917,0.729411764706,0.247058838489,1],"ix":4},"o":{"a":0,"k":100,"ix":5},"r":1,"bm":0,"nm":"Fill 1","mn":"ADBE Vector Graphic - Fill","hd":false},{"ty":"tr","p":{"a":0,"k":[117.345,26.447],"ix":2},"a":{"a":0,"k":[0,0],"ix":1},"s":{"a":0,"k":[100,100],"ix":3},"r":{"a":0,"k":0,"ix":6},"o":{"a":0,"k":100,"ix":7},"sk":{"a":0,"k":0,"ix":4},"sa":{"a":0,"k":0,"ix":5},"nm":"Transform"}],"nm":"Group 4","np":2,"cix":2,"bm":0,"ix":4,"mn":"ADBE Vector Group","hd":false},{"ty":"gr","it":[{"ind":0,"ty":"sh","ix":1,"ks":{"a":0,"k":{"i":[[8.664,0],[0,0],[0,8.664],[0,0],[-8.664,0],[0,0],[0,-8.664],[0,0]],"o":[[0,0],[-8.664,0],[0,0],[0,-8.664],[0,0],[8.664,0],[0,0],[0,8.664]],"v":[[101.407,150.813],[-101.406,150.813],[-117.094,135.125],[-117.094,-135.126],[-101.406,-150.813],[101.407,-150.813],[117.094,-135.126],[117.094,135.125]],"c":true},"ix":2},"nm":"Path 1","mn":"ADBE Vector Shape - Group","hd":false},{"ty":"fl","c":{"a":0,"k":[0.784313785329,0.301960784314,0.301960784314,1],"ix":4},"o":{"a":0,"k":100,"ix":5},"r":1,"bm":0,"nm":"Fill 1","mn":"ADBE Vector Graphic - Fill","hd":false},{"ty":"tr","p":{"a":0,"k":[117.345,187.404],"ix":2},"a":{"a":0,"k":[0,0],"ix":1},"s":{"a":0,"k":[100,100],"ix":3},"r":{"a":0,"k":0,"ix":6},"o":{"a":0,"k":100,"ix":7},"sk":{"a":0,"k":0,"ix":4},"sa":{"a":0,"k":0,"ix":5},"nm":"Transform"}],"nm":"Group 5","np":2,"cix":2,"bm":0,"ix":5,"mn":"ADBE Vector Group","hd":false},{"ty":"tr","p":{"a":0,"k":[146.125,139.429],"ix":2},"a":{"a":0,"k":[117.345,169.234],"ix":1},"s":{"a":0,"k":[100,71],"ix":3},"r":{"a":0,"k":8,"ix":6},"o":{"a":0,"k":100,"ix":7},"sk":{"a":0,"k":-24,"ix":4},"sa":{"a":0,"k":15,"ix":5},"nm":"Transform"}],"nm":"Group 1","np":5,"cix":2,"bm":0,"ix":1,"mn":"ADBE Vector Group","hd":false}],"ip":0,"op":65,"st":0,"ct":1,"bm":0},{"ddd":0,"ind":3,"ty":4,"nm":"R Arm ","parent":17,"sr":1,"ks":{"o":{"a":0,"k":100,"ix":11},"r":{"a":1,"k":[{"i":{"x":[0.25],"y":[1]},"o":{"x":[0.333],"y":[0]},"t":0,"s":[-12]},{"i":{"x":[0.25],"y":[1]},"o":{"x":[0.333],"y":[0]},"t":10,"s":[-18]},{"i":{"x":[0.833],"y":[1]},"o":{"x":[0.333],"y":[0]},"t":25,"s":[22]},{"i":{"x":[0.667],"y":[1]},"o":{"x":[0.167],"y":[0]},"t":30,"s":[19]},{"i":{"x":[0.667],"y":[1]},"o":{"x":[0.333],"y":[0]},"t":35,"s":[27]},{"i":{"x":[0.667],"y":[1]},"o":{"x":[0.333],"y":[0]},"t":40,"s":[24]},{"i":{"x":[0.25],"y":[1]},"o":{"x":[0.333],"y":[0]},"t":45,"s":[22]},{"t":60,"s":[-12]}],"ix":10},"p":{"a":1,"k":[{"i":{"x":0.25,"y":1},"o":{"x":0.333,"y":0},"t":0,"s":[475.842,245.158,0],"to":[0,0,0],"ti":[0,0,0]},{"i":{"x":0.25,"y":0.25},"o":{"x":0.333,"y":0.333},"t":10,"s":[470.387,245.158,0],"to":[0,0,0],"ti":[0,0,0]},{"i":{"x":0.667,"y":1},"o":{"x":0.333,"y":0},"t":25,"s":[470.387,245.158,0],"to":[0,0,0],"ti":[0,0,0]},{"i":{"x":0.667,"y":1},"o":{"x":0.333,"y":0},"t":30,"s":[470.387,247.158,0],"to":[0,0,0],"ti":[0,0,0]},{"i":{"x":0.667,"y":1},"o":{"x":0.333,"y":0},"t":35,"s":[470.387,245.158,0],"to":[0,0,0],"ti":[0,0,0]},{"i":{"x":0.667,"y":1},"o":{"x":0.333,"y":0},"t":40,"s":[470.387,247.158,0],"to":[0,0,0],"ti":[0,0,0]},{"i":{"x":0.25,"y":1},"o":{"x":0.333,"y":0},"t":45,"s":[470.387,245.158,0],"to":[0,0,0],"ti":[0,0,0]},{"t":60,"s":[475.842,245.158,0]}],"ix":2,"l":2},"a":{"a":0,"k":[120.135,8.803,0],"ix":1,"l":2},"s":{"a":0,"k":[-100,100,100],"ix":6,"l":2}},"ao":0,"shapes":[{"ty":"gr","it":[{"ind":0,"ty":"sh","ix":1,"ks":{"a":0,"k":{"i":[[0,0],[6.377,-61.381],[-15.259,18.021],[58.685,67.327]],"o":[[0,0],[-16.604,159.835],[29.977,-35.402],[-19.589,-22.474]],"v":[[48.833,-86.009],[-18.102,-0.938],[137.144,158.15],[66.609,28.844]],"c":true},"ix":2},"nm":"Path 1","mn":"ADBE Vector Shape - Group","hd":false},{"ty":"fl","c":{"a":0,"k":[0.098039223166,0.098039223166,0.098039223166,1],"ix":4},"o":{"a":0,"k":100,"ix":5},"r":1,"bm":0,"nm":"Fill 1","mn":"ADBE Vector Graphic - Fill","hd":false},{"ty":"tr","p":{"a":0,"k":[71.215,86.259],"ix":2},"a":{"a":0,"k":[0,0],"ix":1},"s":{"a":0,"k":[100,100],"ix":3},"r":{"a":0,"k":0,"ix":6},"o":{"a":0,"k":100,"ix":7},"sk":{"a":0,"k":0,"ix":4},"sa":{"a":0,"k":0,"ix":5},"nm":"Transform"}],"nm":"Group 1","np":2,"cix":2,"bm":0,"ix":1,"mn":"ADBE Vector Group","hd":false}],"ip":0,"op":65,"st":0,"ct":1,"bm":0},{"ddd":0,"ind":4,"ty":4,"nm":"Pencil","parent":3,"sr":1,"ks":{"o":{"a":0,"k":100,"ix":11},"r":{"a":1,"k":[{"i":{"x":[0.25],"y":[1]},"o":{"x":[0.167],"y":[0]},"t":0,"s":[53]},{"i":{"x":[0.15],"y":[1]},"o":{"x":[0.333],"y":[0]},"t":10,"s":[40]},{"i":{"x":[0.833],"y":[1]},"o":{"x":[0.333],"y":[0]},"t":25,"s":[166]},{"i":{"x":[0.15],"y":[1]},"o":{"x":[0.167],"y":[0]},"t":30,"s":[170]},{"i":{"x":[0.833],"y":[1]},"o":{"x":[0.333],"y":[0]},"t":35,"s":[166]},{"i":{"x":[0.15],"y":[1]},"o":{"x":[0.167],"y":[0]},"t":40,"s":[170]},{"i":{"x":[0.25],"y":[1]},"o":{"x":[0.333],"y":[0]},"t":45,"s":[166]},{"t":60,"s":[53]}],"ix":10},"p":{"a":1,"k":[{"i":{"x":0.25,"y":0.25},"o":{"x":0.333,"y":0.333},"t":0,"s":[198.627,209.692,0],"to":[0,0,0],"ti":[0,0,0]},{"i":{"x":0.25,"y":1},"o":{"x":0.333,"y":0},"t":10,"s":[198.627,209.692,0],"to":[0,0,0],"ti":[0,0,0]},{"i":{"x":0.667,"y":0.667},"o":{"x":0.333,"y":0.333},"t":25,"s":[191.296,187.08,0],"to":[0,0,0],"ti":[0,0,0]},{"i":{"x":0.667,"y":0.667},"o":{"x":0.333,"y":0.333},"t":30,"s":[191.296,187.08,0],"to":[0,0,0],"ti":[0,0,0]},{"i":{"x":0.667,"y":0.667},"o":{"x":0.333,"y":0.333},"t":35,"s":[191.296,187.08,0],"to":[0,0,0],"ti":[0,0,0]},{"i":{"x":0.667,"y":0.667},"o":{"x":0.333,"y":0.333},"t":40,"s":[191.296,187.08,0],"to":[0,0,0],"ti":[0,0,0]},{"i":{"x":0.25,"y":1},"o":{"x":0.333,"y":0},"t":45,"s":[191.296,187.08,0],"to":[0,0,0],"ti":[0,0,0]},{"t":60,"s":[198.627,209.692,0]}],"ix":2,"l":2},"a":{"a":0,"k":[33.626,152.356,0],"ix":1,"l":2},"s":{"a":0,"k":[-81.818,81.818,100],"ix":6,"l":2}},"ao":0,"shapes":[{"ty":"gr","it":[{"ind":0,"ty":"sh","ix":1,"ks":{"a":0,"k":{"i":[[7.676,0],[0,0],[0,2.7],[0,0],[0,0],[0,0]],"o":[[0,0],[6.931,-1.994],[0,0],[0,0],[0,0],[0,7.676]],"v":[[-1.885,28.022],[-12.013,28.022],[-5.562,19.604],[-5.562,-28.022],[12.013,-28.022],[12.013,14.124]],"c":true},"ix":2},"nm":"Path 1","mn":"ADBE Vector Shape - Group","hd":false},{"ty":"fl","c":{"a":0,"k":[0.670588235294,0.219607858097,0.211764720842,1],"ix":4},"o":{"a":0,"k":100,"ix":5},"r":1,"bm":0,"nm":"Fill 1","mn":"ADBE Vector Graphic - Fill","hd":false},{"ty":"tr","p":{"a":0,"k":[54.989,276.44],"ix":2},"a":{"a":0,"k":[0,0],"ix":1},"s":{"a":0,"k":[100,100],"ix":3},"r":{"a":0,"k":0,"ix":6},"o":{"a":0,"k":100,"ix":7},"sk":{"a":0,"k":0,"ix":4},"sa":{"a":0,"k":0,"ix":5},"nm":"Transform"}],"nm":"Group 1","np":2,"cix":2,"bm":0,"ix":1,"mn":"ADBE Vector Group","hd":false},{"ty":"gr","it":[{"ind":0,"ty":"sh","ix":1,"ks":{"a":0,"k":{"i":[[0,0],[0,0],[0,0],[0,0]],"o":[[0,0],[0,0],[0,0],[0,0]],"v":[[8.787,23.149],[-8.787,23.149],[-8.787,-23.149],[8.787,-23.149]],"c":true},"ix":2},"nm":"Path 1","mn":"ADBE Vector Shape - Group","hd":false},{"ty":"fl","c":{"a":0,"k":[0.823529471603,0.823529471603,0.823529471603,1],"ix":4},"o":{"a":0,"k":100,"ix":5},"r":1,"bm":0,"nm":"Fill 1","mn":"ADBE Vector Graphic - Fill","hd":false},{"ty":"tr","p":{"a":0,"k":[58.215,225.269],"ix":2},"a":{"a":0,"k":[0,0],"ix":1},"s":{"a":0,"k":[100,100],"ix":3},"r":{"a":0,"k":0,"ix":6},"o":{"a":0,"k":100,"ix":7},"sk":{"a":0,"k":0,"ix":4},"sa":{"a":0,"k":0,"ix":5},"nm":"Transform"}],"nm":"Group 2","np":2,"cix":2,"bm":0,"ix":2,"mn":"ADBE Vector Group","hd":false},{"ty":"gr","it":[{"ind":0,"ty":"sh","ix":1,"ks":{"a":0,"k":{"i":[[0,0],[0,0],[0,0],[0,0],[0,0]],"o":[[0,0],[0,0],[0,0],[0,0],[0,0]],"v":[[0.295,-72.77],[8.787,-66.051],[8.787,72.77],[-8.787,72.77],[-8.787,-66.051]],"c":true},"ix":2},"nm":"Path 1","mn":"ADBE Vector Shape - Group","hd":false},{"ty":"fl","c":{"a":0,"k":[0.90588241278,0.662745098039,0.219607858097,1],"ix":4},"o":{"a":0,"k":100,"ix":5},"r":1,"bm":0,"nm":"Fill 1","mn":"ADBE Vector Graphic - Fill","hd":false},{"ty":"tr","p":{"a":0,"k":[58.215,129.35],"ix":2},"a":{"a":0,"k":[0,0],"ix":1},"s":{"a":0,"k":[100,100],"ix":3},"r":{"a":0,"k":0,"ix":6},"o":{"a":0,"k":100,"ix":7},"sk":{"a":0,"k":0,"ix":4},"sa":{"a":0,"k":0,"ix":5},"nm":"Transform"}],"nm":"Group 3","np":2,"cix":2,"bm":0,"ix":3,"mn":"ADBE Vector Group","hd":false},{"ty":"gr","it":[{"ind":0,"ty":"sh","ix":1,"ks":{"a":0,"k":{"i":[[0,0],[8.964,4.497],[0,0],[-1.013,-1.998]],"o":[[-2.989,2.404],[0,0],[1.013,-1.998],[0,0]],"v":[[9.21,5.298],[-9.21,5.475],[-2.395,-7.974],[2.485,-7.974]],"c":true},"ix":2},"nm":"Path 1","mn":"ADBE Vector Shape - Group","hd":false},{"ty":"fl","c":{"a":0,"k":[0.239215701234,0.239215701234,0.223529426724,1],"ix":4},"o":{"a":0,"k":100,"ix":5},"r":1,"bm":0,"nm":"Fill 1","mn":"ADBE Vector Graphic - Fill","hd":false},{"ty":"tr","p":{"a":0,"k":[33.581,10.222],"ix":2},"a":{"a":0,"k":[0,0],"ix":1},"s":{"a":0,"k":[100,100],"ix":3},"r":{"a":0,"k":0,"ix":6},"o":{"a":0,"k":100,"ix":7},"sk":{"a":0,"k":0,"ix":4},"sa":{"a":0,"k":0,"ix":5},"nm":"Transform"}],"nm":"Group 4","np":2,"cix":2,"bm":0,"ix":4,"mn":"ADBE Vector Group","hd":false},{"ty":"gr","it":[{"ind":0,"ty":"sh","ix":1,"ks":{"a":0,"k":{"i":[[-7.676,0],[0,0],[0,7.676],[0,0],[0,0],[0,0]],"o":[[0,0],[7.676,0],[0,0],[0,0],[0,0],[0,7.676]],"v":[[-19.478,28.022],[19.478,28.022],[33.376,14.124],[33.376,-28.022],[-33.376,-28.022],[-33.376,14.124]],"c":true},"ix":2},"nm":"Path 1","mn":"ADBE Vector Shape - Group","hd":false},{"ty":"fl","c":{"a":0,"k":[0.784313785329,0.301960784314,0.301960784314,1],"ix":4},"o":{"a":0,"k":100,"ix":5},"r":1,"bm":0,"nm":"Fill 1","mn":"ADBE Vector Graphic - Fill","hd":false},{"ty":"tr","p":{"a":0,"k":[33.626,276.44],"ix":2},"a":{"a":0,"k":[0,0],"ix":1},"s":{"a":0,"k":[100,100],"ix":3},"r":{"a":0,"k":0,"ix":6},"o":{"a":0,"k":100,"ix":7},"sk":{"a":0,"k":0,"ix":4},"sa":{"a":0,"k":0,"ix":5},"nm":"Transform"}],"nm":"Group 5","np":2,"cix":2,"bm":0,"ix":5,"mn":"ADBE Vector Group","hd":false},{"ty":"gr","it":[{"ind":0,"ty":"sh","ix":1,"ks":{"a":0,"k":{"i":[[0,0],[0,0],[0,0],[0,0]],"o":[[0,0],[0,0],[0,0],[0,0]],"v":[[-33.376,23.149],[33.376,23.149],[33.376,-23.149],[-33.376,-23.149]],"c":true},"ix":2},"nm":"Path 1","mn":"ADBE Vector Shape - Group","hd":false},{"ty":"fl","c":{"a":0,"k":[0.894117706897,0.894117706897,0.894117706897,1],"ix":4},"o":{"a":0,"k":100,"ix":5},"r":1,"bm":0,"nm":"Fill 1","mn":"ADBE Vector Graphic - Fill","hd":false},{"ty":"tr","p":{"a":0,"k":[33.626,225.269],"ix":2},"a":{"a":0,"k":[0,0],"ix":1},"s":{"a":0,"k":[100,100],"ix":3},"r":{"a":0,"k":0,"ix":6},"o":{"a":0,"k":100,"ix":7},"sk":{"a":0,"k":0,"ix":4},"sa":{"a":0,"k":0,"ix":5},"nm":"Transform"}],"nm":"Group 6","np":2,"cix":2,"bm":0,"ix":6,"mn":"ADBE Vector Group","hd":false},{"ty":"gr","it":[{"ind":0,"ty":"sh","ix":1,"ks":{"a":0,"k":{"i":[[0,0],[0,0],[0,0],[0,0],[0,0],[0,0],[0,0],[0,0],[0,0]],"o":[[0,0],[0,0],[0,0],[0,0],[0,0],[0,0],[0,0],[0,0],[0,0]],"v":[[33.376,72.77],[33.376,-66.051],[24.884,-72.77],[15.802,-66.051],[0,-72.77],[-16.54,-66.051],[-24.958,-72.77],[-33.376,-66.051],[-33.376,72.77]],"c":true},"ix":2},"nm":"Path 1","mn":"ADBE Vector Shape - Group","hd":false},{"ty":"fl","c":{"a":0,"k":[0.925490255917,0.729411764706,0.247058838489,1],"ix":4},"o":{"a":0,"k":100,"ix":5},"r":1,"bm":0,"nm":"Fill 1","mn":"ADBE Vector Graphic - Fill","hd":false},{"ty":"tr","p":{"a":0,"k":[33.626,129.35],"ix":2},"a":{"a":0,"k":[0,0],"ix":1},"s":{"a":0,"k":[100,100],"ix":3},"r":{"a":0,"k":0,"ix":6},"o":{"a":0,"k":100,"ix":7},"sk":{"a":0,"k":0,"ix":4},"sa":{"a":0,"k":0,"ix":5},"nm":"Transform"}],"nm":"Group 7","np":2,"cix":2,"bm":0,"ix":7,"mn":"ADBE Vector Group","hd":false},{"ty":"gr","it":[{"ind":0,"ty":"sh","ix":1,"ks":{"a":0,"k":{"i":[[0,0],[0,0],[0,0],[0,0],[0,0],[0,0]],"o":[[0,0],[0,0],[0,0],[0,0],[0,0],[0,0]],"v":[[-9.896,-28.452],[16.711,24.053],[9.495,28.452],[-0.864,24.053],[-16.711,-20.973],[-16.711,-28.452]],"c":true},"ix":2},"nm":"Path 1","mn":"ADBE Vector Shape - Group","hd":false},{"ty":"fl","c":{"a":0,"k":[0.886274569642,0.800000059838,0.607843137255,1],"ix":4},"o":{"a":0,"k":100,"ix":5},"r":1,"bm":0,"nm":"Fill 1","mn":"ADBE Vector Graphic - Fill","hd":false},{"ty":"tr","p":{"a":0,"k":[50.292,39.247],"ix":2},"a":{"a":0,"k":[0,0],"ix":1},"s":{"a":0,"k":[100,100],"ix":3},"r":{"a":0,"k":0,"ix":6},"o":{"a":0,"k":100,"ix":7},"sk":{"a":0,"k":0,"ix":4},"sa":{"a":0,"k":0,"ix":5},"nm":"Transform"}],"nm":"Group 8","np":2,"cix":2,"bm":0,"ix":8,"mn":"ADBE Vector Group","hd":false},{"ty":"gr","it":[{"ind":0,"ty":"sh","ix":1,"ks":{"a":0,"k":{"i":[[0,0],[0,0],[1.796,-3.544],[0,0],[0,0]],"o":[[0,0],[-1.796,-3.544],[0,0],[0,0],[0,0]],"v":[[33.376,26.743],[4.327,-30.583],[-4.327,-30.583],[-33.376,26.743],[21.266,34.127]],"c":true},"ix":2},"nm":"Path 1","mn":"ADBE Vector Shape - Group","hd":false},{"ty":"fl","c":{"a":0,"k":[0.937254961799,0.862745157878,0.682352941176,1],"ix":4},"o":{"a":0,"k":100,"ix":5},"r":1,"bm":0,"nm":"Fill 1","mn":"ADBE Vector Graphic - Fill","hd":false},{"ty":"tr","p":{"a":0,"k":[33.626,36.557],"ix":2},"a":{"a":0,"k":[0,0],"ix":1},"s":{"a":0,"k":[100,100],"ix":3},"r":{"a":0,"k":0,"ix":6},"o":{"a":0,"k":100,"ix":7},"sk":{"a":0,"k":0,"ix":4},"sa":{"a":0,"k":0,"ix":5},"nm":"Transform"}],"nm":"Group 9","np":2,"cix":2,"bm":0,"ix":9,"mn":"ADBE Vector Group","hd":false}],"ip":0,"op":65,"st":0,"ct":1,"bm":0},{"ddd":0,"ind":5,"ty":4,"nm":"Hair","parent":17,"sr":1,"ks":{"o":{"a":0,"k":100,"ix":11},"r":{"a":1,"k":[{"i":{"x":[0.25],"y":[1]},"o":{"x":[0.333],"y":[0]},"t":0,"s":[0]},{"i":{"x":[0.25],"y":[1]},"o":{"x":[0.333],"y":[0]},"t":10,"s":[7]},{"i":{"x":[0.25],"y":[1]},"o":{"x":[0.167],"y":[0]},"t":25,"s":[-7]},{"i":{"x":[0.25],"y":[1]},"o":{"x":[0.167],"y":[0]},"t":45,"s":[-7]},{"t":60,"s":[0]}],"ix":10},"p":{"a":1,"k":[{"i":{"x":0.25,"y":1},"o":{"x":0.333,"y":0},"t":0,"s":[277.391,29.248,0],"to":[0,0,0],"ti":[0,0,0]},{"i":{"x":0.25,"y":1},"o":{"x":0.333,"y":0},"t":10,"s":[277.486,32.883,0],"to":[0,0,0],"ti":[0,0,0]},{"i":{"x":0.25,"y":0.25},"o":{"x":0.333,"y":0.333},"t":25,"s":[277.882,23.801,0],"to":[0,0,0],"ti":[0,0,0]},{"i":{"x":0.25,"y":1},"o":{"x":0.333,"y":0},"t":45,"s":[277.882,23.801,0],"to":[0,0,0],"ti":[0,0,0]},{"t":60,"s":[277.391,29.248,0]}],"ix":2,"l":2},"a":{"a":0,"k":[110.04,67.724,0],"ix":1,"l":2},"s":{"a":0,"k":[100,100,100],"ix":6,"l":2}},"ao":0,"shapes":[{"ty":"gr","it":[{"ind":0,"ty":"sh","ix":1,"ks":{"a":1,"k":[{"i":{"x":0.25,"y":1},"o":{"x":0.333,"y":0},"t":10,"s":[{"i":[[0,0],[1.18,-0.014],[13.673,-16.684],[0.061,-6.031],[0.51,0.728],[-1.64,15.848],[-4.896,2.304],[18.182,-24.84],[0.008,0.644],[-17.594,14.028],[0,0],[32.894,-10.11],[-0.251,0.555],[-21.012,4.364],[-9.173,-22.41],[0.005,-0.758]],"o":[[-0.008,1.181],[-9.179,0.108],[-12.962,15.815],[-0.009,0.889],[-3.303,-4.718],[2.474,-23.914],[0,0],[-0.38,0.52],[-0.082,-5.836],[21.31,-16.99],[0,0],[-0.581,0.179],[2.117,-4.691],[24.57,-5.103],[0.287,0.701],[0,0]],"v":[[54.581,4.924],[52.45,7.079],[-6.917,25.364],[-21.562,62.156],[-23.219,62.669],[-31.539,30.403],[-7.637,-4.154],[-53.464,18.751],[-54.673,18.4],[-35.859,-19.417],[5.034,-30.36],[-40.17,-33.12],[-41.043,-34.056],[-9.557,-58.294],[54.339,-21.343],[54.75,-19.131]],"c":true}]},{"i":{"x":0.25,"y":1},"o":{"x":0.333,"y":0},"t":25,"s":[{"i":[[0,0],[1.18,-0.014],[20.528,-15.707],[0.061,-6.031],[0.51,0.728],[-1.64,15.848],[-4.896,2.304],[18.182,-24.84],[0.008,0.644],[-17.594,14.028],[0,0],[32.894,-10.11],[-0.251,0.555],[-21.012,4.364],[-9.173,-22.41],[0.005,-0.758]],"o":[[-0.008,1.181],[-9.179,0.108],[-16.239,12.426],[-0.009,0.889],[-3.303,-4.718],[2.474,-23.914],[0,0],[-0.38,0.52],[-0.082,-5.836],[21.31,-16.99],[0,0],[-0.581,0.179],[2.117,-4.691],[24.57,-5.103],[0.287,0.701],[0,0]],"v":[[54.581,4.924],[52.45,7.079],[-12.276,19.368],[-29.614,55.673],[-31.271,56.186],[-38.482,24.255],[-6.923,-6.825],[-52.75,16.08],[-53.959,15.729],[-35.145,-22.088],[5.034,-30.36],[-43.32,-28.857],[-44.193,-29.793],[-12.707,-54.031],[54.339,-21.343],[54.75,-19.131]],"c":true}]},{"i":{"x":0.25,"y":1},"o":{"x":0.333,"y":0},"t":45,"s":[{"i":[[0,0],[1.18,-0.014],[20.528,-15.707],[0.061,-6.031],[0.51,0.728],[-1.64,15.848],[-4.896,2.304],[18.182,-24.84],[0.008,0.644],[-17.594,14.028],[0,0],[32.894,-10.11],[-0.251,0.555],[-21.012,4.364],[-9.173,-22.41],[0.005,-0.758]],"o":[[-0.008,1.181],[-9.179,0.108],[-16.239,12.426],[-0.009,0.889],[-3.303,-4.718],[2.474,-23.914],[0,0],[-0.38,0.52],[-0.082,-5.836],[21.31,-16.99],[0,0],[-0.581,0.179],[2.117,-4.691],[24.57,-5.103],[0.287,0.701],[0,0]],"v":[[54.581,4.924],[52.45,7.079],[-12.276,19.368],[-29.614,55.673],[-31.271,56.186],[-38.482,24.255],[-6.923,-6.825],[-52.75,16.08],[-53.959,15.729],[-35.145,-22.088],[5.034,-30.36],[-43.32,-28.857],[-44.193,-29.793],[-12.707,-54.031],[54.339,-21.343],[54.75,-19.131]],"c":true}]},{"t":60,"s":[{"i":[[0,0],[1.18,-0.014],[13.673,-16.684],[0.061,-6.031],[0.51,0.728],[-1.64,15.848],[-4.896,2.304],[18.182,-24.84],[0.008,0.644],[-17.594,14.028],[0,0],[32.894,-10.11],[-0.251,0.555],[-21.012,4.364],[-9.173,-22.41],[0.005,-0.758]],"o":[[-0.008,1.181],[-9.179,0.108],[-12.962,15.815],[-0.009,0.889],[-3.303,-4.718],[2.474,-23.914],[0,0],[-0.38,0.52],[-0.082,-5.836],[21.31,-16.99],[0,0],[-0.581,0.179],[2.117,-4.691],[24.57,-5.103],[0.287,0.701],[0,0]],"v":[[54.581,4.924],[52.45,7.079],[-6.917,25.364],[-21.562,62.156],[-23.219,62.669],[-31.539,30.403],[-7.637,-4.154],[-53.464,18.751],[-54.673,18.4],[-35.859,-19.417],[5.034,-30.36],[-40.17,-33.12],[-41.043,-34.056],[-9.557,-58.294],[54.339,-21.343],[54.75,-19.131]],"c":true}]}],"ix":2},"nm":"Path 1","mn":"ADBE Vector Shape - Group","hd":false},{"ty":"fl","c":{"a":0,"k":[0.227450995352,0.223529426724,0.223529426724,1],"ix":4},"o":{"a":0,"k":100,"ix":5},"r":1,"bm":0,"nm":"Fill 1","mn":"ADBE Vector Graphic - Fill","hd":false},{"ty":"tr","p":{"a":0,"k":[55.005,63.647],"ix":2},"a":{"a":0,"k":[0,0],"ix":1},"s":{"a":0,"k":[100,100],"ix":3},"r":{"a":0,"k":0,"ix":6},"o":{"a":0,"k":100,"ix":7},"sk":{"a":0,"k":0,"ix":4},"sa":{"a":0,"k":0,"ix":5},"nm":"Transform"}],"nm":"Group 1","np":2,"cix":2,"bm":0,"ix":1,"mn":"ADBE Vector Group","hd":false}],"ip":0,"op":65,"st":0,"ct":1,"bm":0},{"ddd":0,"ind":6,"ty":4,"nm":"R Blush","parent":16,"sr":1,"ks":{"o":{"a":0,"k":100,"ix":11},"r":{"a":0,"k":0,"ix":10},"p":{"a":1,"k":[{"i":{"x":0.25,"y":0.25},"o":{"x":0.333,"y":0.333},"t":0,"s":[301.244,164.95,0],"to":[0,0,0],"ti":[0,0,0]},{"i":{"x":0.25,"y":1},"o":{"x":0.333,"y":0},"t":10,"s":[301.244,164.95,0],"to":[0,0,0],"ti":[0,0,0]},{"i":{"x":0.667,"y":0.667},"o":{"x":0.333,"y":0.333},"t":25,"s":[301.244,185.95,0],"to":[0,0,0],"ti":[0,0,0]},{"i":{"x":0.25,"y":1},"o":{"x":0.333,"y":0},"t":45,"s":[301.244,185.95,0],"to":[0,0,0],"ti":[0,0,0]},{"t":60,"s":[301.244,164.95,0]}],"ix":2,"l":2},"a":{"a":0,"k":[29.631,14.482,0],"ix":1,"l":2},"s":{"a":0,"k":[100,100,100],"ix":6,"l":2}},"ao":0,"shapes":[{"ty":"gr","it":[{"ind":0,"ty":"sh","ix":1,"ks":{"a":0,"k":{"i":[[0,-7.86],[16.226,0],[0,7.86],[-16.227,0]],"o":[[0,7.86],[-16.227,0],[0,-7.86],[16.226,0]],"v":[[29.38,0],[0,14.232],[-29.38,0],[0,-14.232]],"c":true},"ix":2},"nm":"Path 1","mn":"ADBE Vector Shape - Group","hd":false},{"ty":"fl","c":{"a":0,"k":[0.87450986376,0.588235294118,0.592156862745,1],"ix":4},"o":{"a":0,"k":100,"ix":5},"r":1,"bm":0,"nm":"Fill 1","mn":"ADBE Vector Graphic - Fill","hd":false},{"ty":"tr","p":{"a":0,"k":[29.631,14.482],"ix":2},"a":{"a":0,"k":[0,0],"ix":1},"s":{"a":0,"k":[100,100],"ix":3},"r":{"a":0,"k":0,"ix":6},"o":{"a":0,"k":100,"ix":7},"sk":{"a":0,"k":0,"ix":4},"sa":{"a":0,"k":0,"ix":5},"nm":"Transform"}],"nm":"Group 1","np":2,"cix":2,"bm":0,"ix":1,"mn":"ADBE Vector Group","hd":false}],"ip":0,"op":65,"st":0,"ct":1,"bm":0},{"ddd":0,"ind":7,"ty":4,"nm":"L Blush","parent":16,"sr":1,"ks":{"o":{"a":0,"k":100,"ix":11},"r":{"a":0,"k":0,"ix":10},"p":{"a":1,"k":[{"i":{"x":0.25,"y":0.25},"o":{"x":0.333,"y":0.333},"t":0,"s":[95.437,164.95,0],"to":[0,0,0],"ti":[0,0,0]},{"i":{"x":0.25,"y":1},"o":{"x":0.333,"y":0},"t":10,"s":[95.437,164.95,0],"to":[0,0,0],"ti":[0,0,0]},{"i":{"x":0.667,"y":0.667},"o":{"x":0.333,"y":0.333},"t":25,"s":[95.437,185.95,0],"to":[0,0,0],"ti":[0,0,0]},{"i":{"x":0.25,"y":1},"o":{"x":0.333,"y":0},"t":45,"s":[95.437,185.95,0],"to":[0,0,0],"ti":[0,0,0]},{"t":60,"s":[95.437,164.95,0]}],"ix":2,"l":2},"a":{"a":0,"k":[29.631,14.482,0],"ix":1,"l":2},"s":{"a":0,"k":[100,100,100],"ix":6,"l":2}},"ao":0,"shapes":[{"ty":"gr","it":[{"ind":0,"ty":"sh","ix":1,"ks":{"a":0,"k":{"i":[[0,-7.86],[16.226,0],[0,7.86],[-16.227,0]],"o":[[0,7.86],[-16.227,0],[0,-7.86],[16.226,0]],"v":[[29.381,0],[0.001,14.232],[-29.381,0],[0.001,-14.232]],"c":true},"ix":2},"nm":"Path 1","mn":"ADBE Vector Shape - Group","hd":false},{"ty":"fl","c":{"a":0,"k":[0.87450986376,0.588235294118,0.592156862745,1],"ix":4},"o":{"a":0,"k":100,"ix":5},"r":1,"bm":0,"nm":"Fill 1","mn":"ADBE Vector Graphic - Fill","hd":false},{"ty":"tr","p":{"a":0,"k":[29.63,14.482],"ix":2},"a":{"a":0,"k":[0,0],"ix":1},"s":{"a":0,"k":[100,100],"ix":3},"r":{"a":0,"k":0,"ix":6},"o":{"a":0,"k":100,"ix":7},"sk":{"a":0,"k":0,"ix":4},"sa":{"a":0,"k":0,"ix":5},"nm":"Transform"}],"nm":"Group 1","np":2,"cix":2,"bm":0,"ix":1,"mn":"ADBE Vector Group","hd":false}],"ip":0,"op":65,"st":0,"ct":1,"bm":0},{"ddd":0,"ind":8,"ty":4,"nm":"Mouth","parent":16,"sr":1,"ks":{"o":{"a":0,"k":100,"ix":11},"r":{"a":0,"k":0,"ix":10},"p":{"a":1,"k":[{"i":{"x":0.25,"y":0.25},"o":{"x":0.333,"y":0.333},"t":0,"s":[199.296,153.212,0],"to":[0,0,0],"ti":[0,0,0]},{"i":{"x":0.25,"y":1},"o":{"x":0.333,"y":0},"t":10,"s":[199.296,153.212,0],"to":[0,0,0],"ti":[0,0,0]},{"i":{"x":0.667,"y":0.667},"o":{"x":0.333,"y":0.333},"t":25,"s":[199.296,168.212,0],"to":[0,0,0],"ti":[0,0,0]},{"i":{"x":0.25,"y":1},"o":{"x":0.333,"y":0},"t":45,"s":[199.296,168.212,0],"to":[0,0,0],"ti":[0,0,0]},{"t":60,"s":[199.296,153.212,0]}],"ix":2,"l":2},"a":{"a":0,"k":[55.041,40.761,0],"ix":1,"l":2},"s":{"a":1,"k":[{"i":{"x":[0.25,0.25,0.833],"y":[1,1,1]},"o":{"x":[0.333,0.333,0.333],"y":[0,0,0]},"t":0,"s":[100,100,100]},{"i":{"x":[0.25,0.25,0.833],"y":[1,1,1]},"o":{"x":[0.333,0.333,0.167],"y":[0,0,0]},"t":10,"s":[100,105,100]},{"i":{"x":[0.25,0.25,0.833],"y":[1,1,1]},"o":{"x":[0.333,0.333,0.167],"y":[0,0,0]},"t":25,"s":[103,100,100]},{"i":{"x":[0.25,0.25,0.667],"y":[1,1,1]},"o":{"x":[0.333,0.333,0.167],"y":[0,0,0]},"t":45,"s":[103,100,100]},{"t":60,"s":[100,100,100]}],"ix":6,"l":2}},"ao":0,"shapes":[{"ty":"gr","it":[{"ind":0,"ty":"sh","ix":1,"ks":{"a":0,"k":{"i":[[-8.501,1.468],[0.316,1.357],[26.518,0],[5.788,-24.749],[-1.379,-0.232],[-14.897,0]],"o":[[1.373,-0.237],[-5.784,-24.755],[-26.514,0],[-0.318,1.361],[8.664,1.456],[15.851,0]],"v":[[52.498,20.011],[54.475,17.08],[-0.001,-26.125],[-54.473,17.068],[-52.488,20.001],[-0.001,26.125]],"c":true},"ix":2},"nm":"Path 1","mn":"ADBE Vector Shape - Group","hd":false},{"ty":"fl","c":{"a":0,"k":[0.929411824544,0.768627510819,0.196078446332,1],"ix":4},"o":{"a":0,"k":100,"ix":5},"r":1,"bm":0,"nm":"Fill 1","mn":"ADBE Vector Graphic - Fill","hd":false},{"ty":"tr","p":{"a":0,"k":[55.041,26.375],"ix":2},"a":{"a":0,"k":[0,0],"ix":1},"s":{"a":0,"k":[100,100],"ix":3},"r":{"a":0,"k":0,"ix":6},"o":{"a":0,"k":100,"ix":7},"sk":{"a":0,"k":0,"ix":4},"sa":{"a":0,"k":0,"ix":5},"nm":"Transform"}],"nm":"Group 1","np":2,"cix":2,"bm":0,"ix":1,"mn":"ADBE Vector Group","hd":false},{"ty":"gr","it":[{"ind":0,"ty":"sh","ix":1,"ks":{"a":0,"k":{"i":[[0,-19.991],[21.312,0],[0,19.991],[-21.312,0]],"o":[[0,19.991],[-21.312,0],[0,-19.991],[21.312,0]],"v":[[38.589,0],[0,36.198],[-38.589,0],[0,-36.198]],"c":true},"ix":2},"nm":"Path 1","mn":"ADBE Vector Shape - Group","hd":false},{"ty":"fl","c":{"a":0,"k":[0.85882358925,0.56862745098,0.188235309077,1],"ix":4},"o":{"a":0,"k":100,"ix":5},"r":1,"bm":0,"nm":"Fill 1","mn":"ADBE Vector Graphic - Fill","hd":false},{"ty":"tr","p":{"a":0,"k":[54.086,45.074],"ix":2},"a":{"a":0,"k":[0,0],"ix":1},"s":{"a":0,"k":[100,100],"ix":3},"r":{"a":0,"k":0,"ix":6},"o":{"a":0,"k":100,"ix":7},"sk":{"a":0,"k":0,"ix":4},"sa":{"a":0,"k":0,"ix":5},"nm":"Transform"}],"nm":"Group 2","np":2,"cix":2,"bm":0,"ix":2,"mn":"ADBE Vector Group","hd":false}],"ip":0,"op":65,"st":0,"ct":1,"bm":0},{"ddd":0,"ind":9,"ty":4,"nm":"4","parent":13,"sr":1,"ks":{"o":{"a":0,"k":100,"ix":11},"r":{"a":0,"k":0,"ix":10},"p":{"a":1,"k":[{"i":{"x":0.667,"y":1},"o":{"x":0.333,"y":0},"t":3,"s":[29.802,-1.905,0],"to":[0,0,0],"ti":[0,0,0]},{"i":{"x":0.667,"y":1},"o":{"x":0.333,"y":0},"t":6,"s":[29.802,43.095,0],"to":[0,0,0],"ti":[0,0,0]},{"i":{"x":0.833,"y":0.833},"o":{"x":0.167,"y":0.167},"t":9,"s":[29.802,-1.905,0],"to":[0,0,0],"ti":[0,0,0]},{"i":{"x":0.667,"y":1},"o":{"x":0.333,"y":0},"t":45,"s":[29.802,-1.905,0],"to":[0,0,0],"ti":[0,0,0]},{"i":{"x":0.667,"y":1},"o":{"x":0.333,"y":0},"t":48,"s":[29.802,43.095,0],"to":[0,0,0],"ti":[0,0,0]},{"t":51,"s":[29.802,-1.905,0]}],"ix":2,"l":2},"a":{"a":0,"k":[-119.715,-72.948,0],"ix":1,"l":2},"s":{"a":0,"k":[92,-92,100],"ix":6,"l":2}},"ao":0,"hasMask":true,"masksProperties":[{"inv":false,"mode":"a","pt":{"a":1,"k":[{"i":{"x":0.667,"y":1},"o":{"x":0.333,"y":0},"t":3,"s":[{"i":[[0,0],[0,0],[-55.121,-3.415]],"o":[[0,0],[0,0],[56.5,3.5]],"v":[[-63.745,-72.948],[-175.745,-72.948],[-121.745,-39.176]],"c":true}]},{"i":{"x":0.667,"y":1},"o":{"x":0.333,"y":0},"t":6,"s":[{"i":[[0,0],[0,0],[-55.121,-3.415]],"o":[[0,0],[0,0],[56.5,3.5]],"v":[[-63.745,-72.948],[-175.745,-72.948],[-121.745,-16.448]],"c":true}]},{"i":{"x":0.833,"y":1},"o":{"x":0.167,"y":0},"t":9,"s":[{"i":[[0,0],[0,0],[-55.121,-3.415]],"o":[[0,0],[0,0],[56.5,3.5]],"v":[[-63.745,-72.948],[-175.745,-72.948],[-121.745,-39.176]],"c":true}]},{"i":{"x":0.667,"y":1},"o":{"x":0.333,"y":0},"t":45,"s":[{"i":[[0,0],[0,0],[-55.121,-3.415]],"o":[[0,0],[0,0],[56.5,3.5]],"v":[[-63.745,-72.948],[-175.745,-72.948],[-121.745,-39.176]],"c":true}]},{"i":{"x":0.667,"y":1},"o":{"x":0.333,"y":0},"t":48,"s":[{"i":[[0,0],[0,0],[-55.121,-3.415]],"o":[[0,0],[0,0],[56.5,3.5]],"v":[[-63.745,-72.948],[-175.745,-72.948],[-121.745,-16.448]],"c":true}]},{"t":51,"s":[{"i":[[0,0],[0,0],[-55.121,-3.415]],"o":[[0,0],[0,0],[56.5,3.5]],"v":[[-63.745,-72.948],[-175.745,-72.948],[-121.745,-39.176]],"c":true}]}],"ix":1},"o":{"a":0,"k":100,"ix":3},"x":{"a":0,"k":0,"ix":4},"nm":"Mask 1"}],"shapes":[{"ty":"gr","it":[{"d":1,"ty":"el","s":{"a":0,"k":[115.23,115.23],"ix":2},"p":{"a":0,"k":[0,0],"ix":3},"nm":"Ellipse Path 1","mn":"ADBE Vector Shape - Ellipse","hd":false},{"ty":"fl","c":{"a":0,"k":[1,1,1,1],"ix":4},"o":{"a":0,"k":100,"ix":5},"r":1,"bm":0,"nm":"Fill 1","mn":"ADBE Vector Graphic - Fill","hd":false},{"ty":"tr","p":{"a":0,"k":[-120.215,-71.631],"ix":2},"a":{"a":0,"k":[0,0],"ix":1},"s":{"a":0,"k":[92.737,92.737],"ix":3},"r":{"a":0,"k":0,"ix":6},"o":{"a":0,"k":100,"ix":7},"sk":{"a":0,"k":0,"ix":4},"sa":{"a":0,"k":0,"ix":5},"nm":"Transform"}],"nm":"Ellipse 1","np":2,"cix":2,"bm":0,"ix":1,"mn":"ADBE Vector Group","hd":false}],"ip":0,"op":65,"st":0,"ct":1,"bm":0},{"ddd":0,"ind":10,"ty":4,"nm":"3","parent":13,"sr":1,"ks":{"o":{"a":0,"k":100,"ix":11},"r":{"a":0,"k":0,"ix":10},"p":{"a":1,"k":[{"i":{"x":0.667,"y":1},"o":{"x":0.333,"y":0},"t":3,"s":[29.802,96.095,0],"to":[0,0,0],"ti":[0,0,0]},{"i":{"x":0.667,"y":1},"o":{"x":0.333,"y":0},"t":6,"s":[29.802,43.095,0],"to":[0,0,0],"ti":[0,0,0]},{"i":{"x":0.833,"y":0.833},"o":{"x":0.167,"y":0.167},"t":9,"s":[29.802,96.095,0],"to":[0,0,0],"ti":[0,0,0]},{"i":{"x":0.667,"y":1},"o":{"x":0.333,"y":0},"t":45,"s":[29.802,96.095,0],"to":[0,0,0],"ti":[0,0,0]},{"i":{"x":0.667,"y":1},"o":{"x":0.333,"y":0},"t":48,"s":[29.802,43.095,0],"to":[0,0,0],"ti":[0,0,0]},{"t":51,"s":[29.802,96.095,0]}],"ix":2,"l":2},"a":{"a":0,"k":[-119.715,-72.948,0],"ix":1,"l":2},"s":{"a":0,"k":[92,92,100],"ix":6,"l":2}},"ao":0,"hasMask":true,"masksProperties":[{"inv":false,"mode":"a","pt":{"a":0,"k":{"i":[[0,0],[0,0],[-55.121,-3.415]],"o":[[0,0],[0,0],[56.5,3.5]],"v":[[-63.745,-72.948],[-175.745,-72.948],[-121.745,-16.448]],"c":true},"ix":1},"o":{"a":0,"k":100,"ix":3},"x":{"a":0,"k":0,"ix":4},"nm":"Mask 1"}],"shapes":[{"ty":"gr","it":[{"d":1,"ty":"el","s":{"a":0,"k":[115.23,115.23],"ix":2},"p":{"a":0,"k":[0,0],"ix":3},"nm":"Ellipse Path 1","mn":"ADBE Vector Shape - Ellipse","hd":false},{"ty":"fl","c":{"a":0,"k":[1,1,1,1],"ix":4},"o":{"a":0,"k":100,"ix":5},"r":1,"bm":0,"nm":"Fill 1","mn":"ADBE Vector Graphic - Fill","hd":false},{"ty":"tr","p":{"a":0,"k":[-120.215,-71.631],"ix":2},"a":{"a":0,"k":[0,0],"ix":1},"s":{"a":0,"k":[92.737,92.737],"ix":3},"r":{"a":0,"k":0,"ix":6},"o":{"a":0,"k":100,"ix":7},"sk":{"a":0,"k":0,"ix":4},"sa":{"a":0,"k":0,"ix":5},"nm":"Transform"}],"nm":"Ellipse 1","np":2,"cix":2,"bm":0,"ix":1,"mn":"ADBE Vector Group","hd":false}],"ip":0,"op":65,"st":0,"ct":1,"bm":0},{"ddd":0,"ind":11,"ty":4,"nm":"2","parent":14,"sr":1,"ks":{"o":{"a":0,"k":100,"ix":11},"r":{"a":0,"k":0,"ix":10},"p":{"a":1,"k":[{"i":{"x":0.667,"y":1},"o":{"x":0.333,"y":0},"t":3,"s":[32.883,-1.905,0],"to":[0,0,0],"ti":[0,0,0]},{"i":{"x":0.667,"y":1},"o":{"x":0.333,"y":0},"t":6,"s":[32.883,43.095,0],"to":[0,0,0],"ti":[0,0,0]},{"i":{"x":0.833,"y":0.833},"o":{"x":0.167,"y":0.167},"t":9,"s":[32.883,-1.905,0],"to":[0,0,0],"ti":[0,0,0]},{"i":{"x":0.667,"y":1},"o":{"x":0.333,"y":0},"t":45,"s":[32.883,-1.905,0],"to":[0,0,0],"ti":[0,0,0]},{"i":{"x":0.667,"y":1},"o":{"x":0.333,"y":0},"t":48,"s":[32.883,43.095,0],"to":[0,0,0],"ti":[0,0,0]},{"t":51,"s":[32.883,-1.905,0]}],"ix":2,"l":2},"a":{"a":0,"k":[-119.715,-72.948,0],"ix":1,"l":2},"s":{"a":0,"k":[92,-92,100],"ix":6,"l":2}},"ao":0,"hasMask":true,"masksProperties":[{"inv":false,"mode":"a","pt":{"a":1,"k":[{"i":{"x":0.667,"y":1},"o":{"x":0.333,"y":0},"t":3,"s":[{"i":[[0,0],[0,0],[-55.121,-3.415]],"o":[[0,0],[0,0],[56.5,3.5]],"v":[[-63.745,-72.948],[-175.745,-72.948],[-121.745,-39.176]],"c":true}]},{"i":{"x":0.667,"y":1},"o":{"x":0.333,"y":0},"t":6,"s":[{"i":[[0,0],[0,0],[-55.121,-3.415]],"o":[[0,0],[0,0],[56.5,3.5]],"v":[[-63.745,-72.948],[-175.745,-72.948],[-121.745,-16.448]],"c":true}]},{"i":{"x":0.833,"y":1},"o":{"x":0.167,"y":0},"t":9,"s":[{"i":[[0,0],[0,0],[-55.121,-3.415]],"o":[[0,0],[0,0],[56.5,3.5]],"v":[[-63.745,-72.948],[-175.745,-72.948],[-121.745,-39.176]],"c":true}]},{"i":{"x":0.667,"y":1},"o":{"x":0.333,"y":0},"t":45,"s":[{"i":[[0,0],[0,0],[-55.121,-3.415]],"o":[[0,0],[0,0],[56.5,3.5]],"v":[[-63.745,-72.948],[-175.745,-72.948],[-121.745,-39.176]],"c":true}]},{"i":{"x":0.667,"y":1},"o":{"x":0.333,"y":0},"t":48,"s":[{"i":[[0,0],[0,0],[-55.121,-3.415]],"o":[[0,0],[0,0],[56.5,3.5]],"v":[[-63.745,-72.948],[-175.745,-72.948],[-121.745,-16.448]],"c":true}]},{"t":51,"s":[{"i":[[0,0],[0,0],[-55.121,-3.415]],"o":[[0,0],[0,0],[56.5,3.5]],"v":[[-63.745,-72.948],[-175.745,-72.948],[-121.745,-39.176]],"c":true}]}],"ix":1},"o":{"a":0,"k":100,"ix":3},"x":{"a":0,"k":0,"ix":4},"nm":"Mask 1"}],"shapes":[{"ty":"gr","it":[{"d":1,"ty":"el","s":{"a":0,"k":[115.23,115.23],"ix":2},"p":{"a":0,"k":[0,0],"ix":3},"nm":"Ellipse Path 1","mn":"ADBE Vector Shape - Ellipse","hd":false},{"ty":"fl","c":{"a":0,"k":[1,1,1,1],"ix":4},"o":{"a":0,"k":100,"ix":5},"r":1,"bm":0,"nm":"Fill 1","mn":"ADBE Vector Graphic - Fill","hd":false},{"ty":"tr","p":{"a":0,"k":[-120.215,-71.631],"ix":2},"a":{"a":0,"k":[0,0],"ix":1},"s":{"a":0,"k":[92.737,92.737],"ix":3},"r":{"a":0,"k":0,"ix":6},"o":{"a":0,"k":100,"ix":7},"sk":{"a":0,"k":0,"ix":4},"sa":{"a":0,"k":0,"ix":5},"nm":"Transform"}],"nm":"Ellipse 1","np":2,"cix":2,"bm":0,"ix":1,"mn":"ADBE Vector Group","hd":false}],"ip":0,"op":65,"st":0,"ct":1,"bm":0},{"ddd":0,"ind":12,"ty":4,"nm":"1","parent":14,"sr":1,"ks":{"o":{"a":0,"k":100,"ix":11},"r":{"a":0,"k":0,"ix":10},"p":{"a":1,"k":[{"i":{"x":0.667,"y":1},"o":{"x":0.333,"y":0},"t":3,"s":[32.883,96.095,0],"to":[0,0,0],"ti":[0,0,0]},{"i":{"x":0.667,"y":1},"o":{"x":0.333,"y":0},"t":6,"s":[32.883,43.095,0],"to":[0,0,0],"ti":[0,0,0]},{"i":{"x":0.833,"y":0.833},"o":{"x":0.167,"y":0.167},"t":9,"s":[32.883,96.095,0],"to":[0,0,0],"ti":[0,0,0]},{"i":{"x":0.667,"y":1},"o":{"x":0.333,"y":0},"t":45,"s":[32.883,96.095,0],"to":[0,0,0],"ti":[0,0,0]},{"i":{"x":0.667,"y":1},"o":{"x":0.333,"y":0},"t":48,"s":[32.883,43.095,0],"to":[0,0,0],"ti":[0,0,0]},{"t":51,"s":[32.883,96.095,0]}],"ix":2,"l":2},"a":{"a":0,"k":[-119.715,-72.948,0],"ix":1,"l":2},"s":{"a":0,"k":[92,92,100],"ix":6,"l":2}},"ao":0,"hasMask":true,"masksProperties":[{"inv":false,"mode":"a","pt":{"a":0,"k":{"i":[[0,0],[0,0],[-55.121,-3.415]],"o":[[0,0],[0,0],[56.5,3.5]],"v":[[-63.745,-72.948],[-175.745,-72.948],[-121.745,-16.448]],"c":true},"ix":1},"o":{"a":0,"k":100,"ix":3},"x":{"a":0,"k":0,"ix":4},"nm":"Mask 1"}],"shapes":[{"ty":"gr","it":[{"d":1,"ty":"el","s":{"a":0,"k":[115.23,115.23],"ix":2},"p":{"a":0,"k":[0,0],"ix":3},"nm":"Ellipse Path 1","mn":"ADBE Vector Shape - Ellipse","hd":false},{"ty":"fl","c":{"a":0,"k":[1,1,1,1],"ix":4},"o":{"a":0,"k":100,"ix":5},"r":1,"bm":0,"nm":"Fill 1","mn":"ADBE Vector Graphic - Fill","hd":false},{"ty":"tr","p":{"a":0,"k":[-120.215,-71.631],"ix":2},"a":{"a":0,"k":[0,0],"ix":1},"s":{"a":0,"k":[92.737,92.737],"ix":3},"r":{"a":0,"k":0,"ix":6},"o":{"a":0,"k":100,"ix":7},"sk":{"a":0,"k":0,"ix":4},"sa":{"a":0,"k":0,"ix":5},"nm":"Transform"}],"nm":"Ellipse 1","np":2,"cix":2,"bm":0,"ix":1,"mn":"ADBE Vector Group","hd":false}],"ip":0,"op":65,"st":0,"ct":1,"bm":0},{"ddd":0,"ind":13,"ty":4,"nm":"R Eye","parent":16,"sr":1,"ks":{"o":{"a":0,"k":100,"ix":11},"r":{"a":0,"k":0,"ix":10},"p":{"a":1,"k":[{"i":{"x":0.25,"y":0.25},"o":{"x":0.333,"y":0.333},"t":0,"s":[301.244,97.298,0],"to":[0,0,0],"ti":[0,0,0]},{"i":{"x":0.25,"y":1},"o":{"x":0.333,"y":0},"t":10,"s":[301.244,97.298,0],"to":[0,0,0],"ti":[0,0,0]},{"i":{"x":0.667,"y":0.667},"o":{"x":0.333,"y":0.333},"t":25,"s":[301.244,120.298,0],"to":[0,0,0],"ti":[0,0,0]},{"i":{"x":0.25,"y":1},"o":{"x":0.333,"y":0},"t":45,"s":[301.244,120.298,0],"to":[0,0,0],"ti":[0,0,0]},{"t":60,"s":[301.244,97.298,0]}],"ix":2,"l":2},"a":{"a":0,"k":[31.974,46.513,0],"ix":1,"l":2},"s":{"a":0,"k":[100,100,100],"ix":6,"l":2}},"ao":0,"shapes":[{"ty":"gr","it":[{"ind":0,"ty":"sh","ix":1,"ks":{"a":0,"k":{"i":[[17.52,0],[0,0],[4.292,-2.167],[0,-5.528],[11.356,0],[0.868,0.112],[0,0],[-17.521,0],[0,17.52],[0,0]],"o":[[0,0],[-5.136,0],[3.55,3.695],[0,11.356],[-0.898,0],[0,0],[0,17.52],[17.52,0],[0,0],[0,-17.521]],"v":[[0,-46.263],[0,-46.263],[-14.262,-42.849],[-8.518,-28.617],[-29.08,-8.055],[-31.724,-8.243],[-31.724,14.541],[0,46.263],[31.724,14.541],[31.724,-14.539]],"c":true},"ix":2},"nm":"Path 1","mn":"ADBE Vector Shape - Group","hd":false},{"ty":"fl","c":{"a":0,"k":[0.211764720842,0.207843152214,0.207843152214,1],"ix":4},"o":{"a":0,"k":100,"ix":5},"r":1,"bm":0,"nm":"Fill 1","mn":"ADBE Vector Graphic - Fill","hd":false},{"ty":"tr","p":{"a":0,"k":[31.974,46.514],"ix":2},"a":{"a":0,"k":[0,0],"ix":1},"s":{"a":0,"k":[100,100],"ix":3},"r":{"a":0,"k":0,"ix":6},"o":{"a":0,"k":100,"ix":7},"sk":{"a":0,"k":0,"ix":4},"sa":{"a":0,"k":0,"ix":5},"nm":"Transform"}],"nm":"Group 1","np":2,"cix":2,"bm":0,"ix":1,"mn":"ADBE Vector Group","hd":false}],"ip":0,"op":65,"st":0,"ct":1,"bm":0},{"ddd":0,"ind":14,"ty":4,"nm":"L Eye","parent":16,"sr":1,"ks":{"o":{"a":0,"k":100,"ix":11},"r":{"a":0,"k":0,"ix":10},"p":{"a":1,"k":[{"i":{"x":0.25,"y":0.25},"o":{"x":0.333,"y":0.333},"t":0,"s":[95.436,97.298,0],"to":[0,0,0],"ti":[0,0,0]},{"i":{"x":0.25,"y":1},"o":{"x":0.333,"y":0},"t":10,"s":[95.436,97.298,0],"to":[0,0,0],"ti":[0,0,0]},{"i":{"x":0.667,"y":0.667},"o":{"x":0.333,"y":0.333},"t":25,"s":[95.436,120.298,0],"to":[0,0,0],"ti":[0,0,0]},{"i":{"x":0.25,"y":1},"o":{"x":0.333,"y":0},"t":45,"s":[95.436,120.298,0],"to":[0,0,0],"ti":[0,0,0]},{"t":60,"s":[95.436,97.298,0]}],"ix":2,"l":2},"a":{"a":0,"k":[31.974,46.513,0],"ix":1,"l":2},"s":{"a":0,"k":[100,100,100],"ix":6,"l":2}},"ao":0,"shapes":[{"ty":"gr","it":[{"ind":0,"ty":"sh","ix":1,"ks":{"a":0,"k":{"i":[[17.52,0],[0,0],[4.292,-2.167],[0,-5.528],[11.356,0],[0.868,0.112],[0,0],[-17.521,0],[0,17.52],[0,0]],"o":[[0,0],[-5.136,0],[3.55,3.695],[0,11.356],[-0.898,0],[0,0],[0,17.52],[17.52,0],[0,0],[0,-17.521]],"v":[[0.001,-46.263],[0.001,-46.263],[-14.261,-42.849],[-8.518,-28.617],[-29.079,-8.055],[-31.723,-8.243],[-31.723,14.541],[0.001,46.263],[31.723,14.541],[31.723,-14.539]],"c":true},"ix":2},"nm":"Path 1","mn":"ADBE Vector Shape - Group","hd":false},{"ty":"fl","c":{"a":0,"k":[0.211764720842,0.207843152214,0.207843152214,1],"ix":4},"o":{"a":0,"k":100,"ix":5},"r":1,"bm":0,"nm":"Fill 1","mn":"ADBE Vector Graphic - Fill","hd":false},{"ty":"tr","p":{"a":0,"k":[31.974,46.514],"ix":2},"a":{"a":0,"k":[0,0],"ix":1},"s":{"a":0,"k":[100,100],"ix":3},"r":{"a":0,"k":0,"ix":6},"o":{"a":0,"k":100,"ix":7},"sk":{"a":0,"k":0,"ix":4},"sa":{"a":0,"k":0,"ix":5},"nm":"Transform"}],"nm":"Group 1","np":2,"cix":2,"bm":0,"ix":1,"mn":"ADBE Vector Group","hd":false}],"ip":0,"op":65,"st":0,"ct":1,"bm":0},{"ddd":0,"ind":15,"ty":4,"nm":"Dots on body","parent":16,"sr":1,"ks":{"o":{"a":0,"k":100,"ix":11},"r":{"a":0,"k":0,"ix":10},"p":{"a":0,"k":[198.012,347.529,0],"ix":2,"l":2},"a":{"a":0,"k":[50.908,23.379,0],"ix":1,"l":2},"s":{"a":0,"k":[100,100,100],"ix":6,"l":2}},"ao":0,"shapes":[{"ty":"gr","it":[{"ind":0,"ty":"sh","ix":1,"ks":{"a":0,"k":{"i":[[1.318,2.283],[0,0],[-2.636,0],[0,0],[1.318,-2.284],[0,0]],"o":[[0,0],[-1.318,-2.284],[0,0],[2.636,0],[0,0],[-1.318,2.283]],"v":[[-2.966,8.751],[-11.423,-5.896],[-8.457,-11.034],[8.457,-11.034],[11.423,-5.896],[2.966,8.751]],"c":true},"ix":2},"nm":"Path 1","mn":"ADBE Vector Shape - Group","hd":false},{"ty":"fl","c":{"a":0,"k":[0.933333393172,0.90588241278,0.90588241278,1],"ix":4},"o":{"a":0,"k":100,"ix":5},"r":1,"bm":0,"nm":"Fill 1","mn":"ADBE Vector Graphic - Fill","hd":false},{"ty":"tr","p":{"a":0,"k":[50.908,35.474],"ix":2},"a":{"a":0,"k":[0,0],"ix":1},"s":{"a":0,"k":[100,100],"ix":3},"r":{"a":0,"k":0,"ix":6},"o":{"a":0,"k":100,"ix":7},"sk":{"a":0,"k":0,"ix":4},"sa":{"a":0,"k":0,"ix":5},"nm":"Transform"}],"nm":"Group 1","np":2,"cix":2,"bm":0,"ix":1,"mn":"ADBE Vector Group","hd":false},{"ty":"gr","it":[{"ind":0,"ty":"sh","ix":1,"ks":{"a":0,"k":{"i":[[1.318,2.283],[0,0],[-2.636,0],[0,0],[1.318,-2.284],[0,0]],"o":[[0,0],[-1.318,-2.284],[0,0],[2.636,0],[0,0],[-1.318,2.283]],"v":[[-2.966,8.751],[-11.423,-5.896],[-8.457,-11.034],[8.457,-11.034],[11.423,-5.896],[2.966,8.751]],"c":true},"ix":2},"nm":"Path 1","mn":"ADBE Vector Shape - Group","hd":false},{"ty":"fl","c":{"a":0,"k":[0.933333393172,0.90588241278,0.90588241278,1],"ix":4},"o":{"a":0,"k":100,"ix":5},"r":1,"bm":0,"nm":"Fill 1","mn":"ADBE Vector Graphic - Fill","hd":false},{"ty":"tr","p":{"a":0,"k":[88.825,11.284],"ix":2},"a":{"a":0,"k":[0,0],"ix":1},"s":{"a":0,"k":[100,100],"ix":3},"r":{"a":0,"k":0,"ix":6},"o":{"a":0,"k":100,"ix":7},"sk":{"a":0,"k":0,"ix":4},"sa":{"a":0,"k":0,"ix":5},"nm":"Transform"}],"nm":"Group 2","np":2,"cix":2,"bm":0,"ix":2,"mn":"ADBE Vector Group","hd":false},{"ty":"gr","it":[{"ind":0,"ty":"sh","ix":1,"ks":{"a":0,"k":{"i":[[1.318,2.283],[0,0],[-2.636,0],[0,0],[1.318,-2.284],[0,0]],"o":[[0,0],[-1.318,-2.284],[0,0],[2.636,0],[0,0],[-1.318,2.283]],"v":[[-2.966,8.751],[-11.423,-5.896],[-8.457,-11.034],[8.457,-11.034],[11.423,-5.896],[2.966,8.751]],"c":true},"ix":2},"nm":"Path 1","mn":"ADBE Vector Shape - Group","hd":false},{"ty":"fl","c":{"a":0,"k":[0.933333393172,0.90588241278,0.90588241278,1],"ix":4},"o":{"a":0,"k":100,"ix":5},"r":1,"bm":0,"nm":"Fill 1","mn":"ADBE Vector Graphic - Fill","hd":false},{"ty":"tr","p":{"a":0,"k":[12.991,11.284],"ix":2},"a":{"a":0,"k":[0,0],"ix":1},"s":{"a":0,"k":[100,100],"ix":3},"r":{"a":0,"k":0,"ix":6},"o":{"a":0,"k":100,"ix":7},"sk":{"a":0,"k":0,"ix":4},"sa":{"a":0,"k":0,"ix":5},"nm":"Transform"}],"nm":"Group 3","np":2,"cix":2,"bm":0,"ix":3,"mn":"ADBE Vector Group","hd":false}],"ip":0,"op":65,"st":0,"ct":1,"bm":0},{"ddd":0,"ind":16,"ty":4,"nm":"Body white","parent":17,"sr":1,"ks":{"o":{"a":0,"k":100,"ix":11},"r":{"a":0,"k":0,"ix":10},"p":{"a":0,"k":[249.3,332.644,0],"ix":2,"l":2},"a":{"a":0,"k":[199.297,222.065,0],"ix":1,"l":2},"s":{"a":0,"k":[100,100,100],"ix":6,"l":2}},"ao":0,"shapes":[{"ty":"gr","it":[{"ind":0,"ty":"sh","ix":1,"ks":{"a":0,"k":{"i":[[5.615,16.104],[0,9.302],[0,0],[47.386,0],[0,-40.022],[0,0],[0,0],[0,0],[0,0],[40.022,0],[0,-47.386],[0,0],[3.063,-8.784],[-5.537,-53.032],[-122.86,0],[-7.296,69.883]],"o":[[-3.062,-8.784],[0,0],[0,-47.386],[-40.022,0],[0,0],[0,0],[0,0],[0,0],[0,-40.022],[-47.386,0],[0,0],[0,9.302],[-5.615,16.104],[7.295,69.883],[122.86,0],[5.536,-53.032]],"v":[[185.275,-34.839],[180.718,-62.163],[180.718,-136.015],[94.918,-221.815],[22.452,-149.349],[22.452,-45.717],[0,-45.717],[-22.452,-45.717],[-22.452,-149.349],[-94.918,-221.815],[-180.718,-136.015],[-180.718,-62.163],[-185.275,-34.839],[-193.51,68.418],[0,221.815],[193.511,68.418]],"c":true},"ix":2},"nm":"Path 1","mn":"ADBE Vector Shape - Group","hd":false},{"ty":"fl","c":{"a":0,"k":[1,1,1,1],"ix":4},"o":{"a":0,"k":100,"ix":5},"r":1,"bm":0,"nm":"Fill 1","mn":"ADBE Vector Graphic - Fill","hd":false},{"ty":"tr","p":{"a":1,"k":[{"i":{"x":0.25,"y":0.25},"o":{"x":0.333,"y":0.333},"t":0,"s":[195.985,445.364],"to":[0,0],"ti":[0,0]},{"i":{"x":0.25,"y":1},"o":{"x":0.333,"y":0},"t":10,"s":[195.985,445.364],"to":[0,0],"ti":[0,0]},{"i":{"x":0.667,"y":0.667},"o":{"x":0.333,"y":0.333},"t":25,"s":[195.985,460.364],"to":[0,0],"ti":[0,0]},{"i":{"x":0.25,"y":1},"o":{"x":0.333,"y":0},"t":45,"s":[195.985,460.364],"to":[0,0],"ti":[0,0]},{"t":60,"s":[195.985,445.364]}],"ix":2},"a":{"a":0,"k":[-3.312,223.3],"ix":1},"s":{"a":1,"k":[{"i":{"x":[0.25,0.25],"y":[1,1]},"o":{"x":[0.333,0.333],"y":[0,0]},"t":10,"s":[100,100]},{"i":{"x":[0.667,0.667],"y":[1,1]},"o":{"x":[0.333,0.333],"y":[0,0]},"t":25,"s":[103,100]},{"i":{"x":[0.25,0.25],"y":[1,1]},"o":{"x":[0.333,0.333],"y":[0,0]},"t":45,"s":[103,100]},{"t":60,"s":[100,100]}],"ix":3},"r":{"a":0,"k":0,"ix":6},"o":{"a":0,"k":100,"ix":7},"sk":{"a":0,"k":0,"ix":4},"sa":{"a":0,"k":0,"ix":5},"nm":"Transform"}],"nm":"Group 1","np":2,"cix":2,"bm":0,"ix":1,"mn":"ADBE Vector Group","hd":false}],"ip":0,"op":65,"st":0,"ct":1,"bm":0},{"ddd":0,"ind":17,"ty":4,"nm":"Body","sr":1,"ks":{"o":{"a":0,"k":100,"ix":11},"r":{"a":1,"k":[{"i":{"x":[0.25],"y":[1]},"o":{"x":[0.333],"y":[0]},"t":0,"s":[0]},{"i":{"x":[0.25],"y":[1]},"o":{"x":[0.333],"y":[0]},"t":10,"s":[0]},{"i":{"x":[0.833],"y":[1]},"o":{"x":[0.333],"y":[0]},"t":25,"s":[-0.5]},{"i":{"x":[0.833],"y":[1]},"o":{"x":[0.167],"y":[0]},"t":37,"s":[0]},{"i":{"x":[0.25],"y":[1]},"o":{"x":[0.167],"y":[0]},"t":49,"s":[-0.5]},{"t":60,"s":[0]}],"ix":10},"p":{"a":1,"k":[{"i":{"x":0.25,"y":0.25},"o":{"x":0.333,"y":0.333},"t":0,"s":[495.803,832.526,0],"to":[0,0,0],"ti":[0,0,0]},{"i":{"x":0.25,"y":1},"o":{"x":0.333,"y":0},"t":10,"s":[495.803,832.526,0],"to":[0,0,0],"ti":[0,0,0]},{"i":{"x":0.667,"y":0.667},"o":{"x":0.333,"y":0.333},"t":25,"s":[495.803,837.526,0],"to":[0,0,0],"ti":[0,0,0]},{"i":{"x":0.25,"y":1},"o":{"x":0.333,"y":0},"t":45,"s":[495.803,837.526,0],"to":[0,0,0],"ti":[0,0,0]},{"t":60,"s":[495.803,832.526,0]}],"ix":2,"l":2},"a":{"a":0,"k":[247.96,603.12,0],"ix":1,"l":2},"s":{"a":0,"k":[110,110,100],"ix":6,"l":2}},"ao":0,"shapes":[{"ty":"gr","it":[{"ind":0,"ty":"sh","ix":1,"ks":{"a":0,"k":{"i":[[5.163,134.46],[0,0],[0,0],[7.172,25.138],[127.866,-5.054],[0.71,-0.005],[0.712,0],[27.19,-95.308],[1.618,-26.09],[0,0],[0,0],[-152.102,0]],"o":[[0,0],[0,0],[-1.618,-26.09],[-27.19,-95.308],[-0.712,0],[-0.71,-0.005],[-127.865,-5.054],[-7.172,25.138],[0,0],[0,0],[-5.163,134.46],[152.102,0]],"v":[[242.547,58.652],[242.547,36.391],[237.711,-41.584],[224.882,-118.74],[2.119,-296.144],[0,-296.102],[-2.119,-296.144],[-224.882,-118.74],[-237.711,-41.584],[-242.547,36.391],[-242.547,58.652],[0,301.198]],"c":true},"ix":2},"nm":"Path 1","mn":"ADBE Vector Shape - Group","hd":false},{"ty":"fl","c":{"a":0,"k":[0.098039223166,0.098039223166,0.098039223166,1],"ix":4},"o":{"a":0,"k":100,"ix":5},"r":1,"bm":0,"nm":"Fill 1","mn":"ADBE Vector Graphic - Fill","hd":false},{"ty":"tr","p":{"a":0,"k":[242.187,605.676],"ix":2},"a":{"a":0,"k":[-5.773,304.227],"ix":1},"s":{"a":1,"k":[{"i":{"x":[0.25,0.25],"y":[1,1]},"o":{"x":[0.333,0.333],"y":[0,0]},"t":10,"s":[100,100]},{"i":{"x":[0.667,0.667],"y":[1,1]},"o":{"x":[0.333,0.333],"y":[0,0]},"t":25,"s":[101,100]},{"i":{"x":[0.25,0.25],"y":[1,1]},"o":{"x":[0.333,0.333],"y":[0,0]},"t":45,"s":[101,100]},{"t":60,"s":[100,100]}],"ix":3},"r":{"a":0,"k":0,"ix":6},"o":{"a":0,"k":100,"ix":7},"sk":{"a":0,"k":0,"ix":4},"sa":{"a":0,"k":0,"ix":5},"nm":"Transform"}],"nm":"Group 1","np":2,"cix":2,"bm":0,"ix":1,"mn":"ADBE Vector Group","hd":false}],"ip":0,"op":65,"st":0,"ct":1,"bm":0},{"ddd":0,"ind":18,"ty":4,"nm":"R Leg","sr":1,"ks":{"o":{"a":0,"k":100,"ix":11},"r":{"a":1,"k":[{"i":{"x":[0.667],"y":[1]},"o":{"x":[0.333],"y":[0]},"t":19,"s":[0]},{"i":{"x":[0.667],"y":[1]},"o":{"x":[0.333],"y":[0]},"t":24,"s":[-10]},{"i":{"x":[0.667],"y":[1]},"o":{"x":[0.333],"y":[0]},"t":29,"s":[0]},{"i":{"x":[0.667],"y":[1]},"o":{"x":[0.333],"y":[0]},"t":34,"s":[-10]},{"i":{"x":[0.667],"y":[1]},"o":{"x":[0.333],"y":[0]},"t":39,"s":[0]},{"i":{"x":[0.667],"y":[1]},"o":{"x":[0.333],"y":[0]},"t":44,"s":[-10]},{"t":49,"s":[0]}],"ix":10},"p":{"a":0,"k":[561.649,821.218,0],"ix":2,"l":2},"a":{"a":0,"k":[6.038,23.08,0],"ix":1,"l":2},"s":{"a":1,"k":[{"i":{"x":[0.25,0.25,0.833],"y":[1,1,1]},"o":{"x":[0.333,0.333,0.333],"y":[0,0,0]},"t":10,"s":[110,110,100]},{"i":{"x":[0.833,0.833,0.833],"y":[1,1,1]},"o":{"x":[0.333,0.333,0.167],"y":[0,0,0]},"t":25,"s":[115,105,100]},{"i":{"x":[0.25,0.25,0.667],"y":[1,1,1]},"o":{"x":[0.167,0.167,0.167],"y":[0,0,0]},"t":45,"s":[115,105,100]},{"t":60,"s":[110,110,100]}],"ix":6,"l":2}},"ao":0,"shapes":[{"ty":"gr","it":[{"ind":0,"ty":"sh","ix":1,"ks":{"a":0,"k":{"i":[[18.237,0],[0,0],[0,18.237],[-18.237,0],[0,0],[0,-18.238]],"o":[[0,0],[-18.237,0],[0,-18.238],[0,0],[18.237,0],[0,18.237]],"v":[[25.763,33.021],[-25.763,33.021],[-58.784,0.001],[-25.763,-33.021],[25.763,-33.021],[58.784,0.001]],"c":true},"ix":2},"nm":"Path 1","mn":"ADBE Vector Shape - Group","hd":false},{"ty":"fl","c":{"a":0,"k":[0.85882358925,0.56862745098,0.188235309077,1],"ix":4},"o":{"a":0,"k":100,"ix":5},"r":1,"bm":0,"nm":"Fill 1","mn":"ADBE Vector Graphic - Fill","hd":false},{"ty":"tr","p":{"a":0,"k":[59.035,33.271],"ix":2},"a":{"a":0,"k":[0,0],"ix":1},"s":{"a":0,"k":[100,100],"ix":3},"r":{"a":0,"k":0,"ix":6},"o":{"a":0,"k":100,"ix":7},"sk":{"a":0,"k":0,"ix":4},"sa":{"a":0,"k":0,"ix":5},"nm":"Transform"}],"nm":"Group 1","np":2,"cix":2,"bm":0,"ix":1,"mn":"ADBE Vector Group","hd":false}],"ip":0,"op":65,"st":0,"ct":1,"bm":0},{"ddd":0,"ind":19,"ty":4,"nm":"L Leg","sr":1,"ks":{"o":{"a":0,"k":100,"ix":11},"r":{"a":0,"k":0,"ix":10},"p":{"a":0,"k":[425.063,821.218,0],"ix":2,"l":2},"a":{"a":0,"k":[105.916,23.08,0],"ix":1,"l":2},"s":{"a":1,"k":[{"i":{"x":[0.25,0.25,0.833],"y":[1,1,1]},"o":{"x":[0.333,0.333,0.333],"y":[0,0,0]},"t":10,"s":[110,110,100]},{"i":{"x":[0.833,0.833,0.833],"y":[1,1,1]},"o":{"x":[0.333,0.333,0.167],"y":[0,0,0]},"t":25,"s":[115,105,100]},{"i":{"x":[0.25,0.25,0.667],"y":[1,1,1]},"o":{"x":[0.167,0.167,0.167],"y":[0,0,0]},"t":45,"s":[115,105,100]},{"t":60,"s":[110,110,100]}],"ix":6,"l":2}},"ao":0,"shapes":[{"ty":"gr","it":[{"ind":0,"ty":"sh","ix":1,"ks":{"a":0,"k":{"i":[[18.237,0],[0,0],[0,18.237],[-18.237,0],[0,0],[0,-18.238]],"o":[[0,0],[-18.237,0],[0,-18.238],[0,0],[18.237,0],[0,18.237]],"v":[[25.764,33.021],[-25.764,33.021],[-58.785,0.001],[-25.764,-33.021],[25.764,-33.021],[58.785,0.001]],"c":true},"ix":2},"nm":"Path 1","mn":"ADBE Vector Shape - Group","hd":false},{"ty":"fl","c":{"a":0,"k":[0.85882358925,0.56862745098,0.188235309077,1],"ix":4},"o":{"a":0,"k":100,"ix":5},"r":1,"bm":0,"nm":"Fill 1","mn":"ADBE Vector Graphic - Fill","hd":false},{"ty":"tr","p":{"a":0,"k":[59.035,33.271],"ix":2},"a":{"a":0,"k":[0,0],"ix":1},"s":{"a":0,"k":[100,100],"ix":3},"r":{"a":0,"k":0,"ix":6},"o":{"a":0,"k":100,"ix":7},"sk":{"a":0,"k":0,"ix":4},"sa":{"a":0,"k":0,"ix":5},"nm":"Transform"}],"nm":"Group 1","np":2,"cix":2,"bm":0,"ix":1,"mn":"ADBE Vector Group","hd":false}],"ip":0,"op":65,"st":0,"ct":1,"bm":0}],"markers":[]}